lemmatizer_be/__about__.py
lemmatizer_be/__init__.py
lemmatizer_be/_timeit.py
lemmatizer_be/_utils.py
lemmatizer_be/generate.py
lemmatizer_be/lemmatizer.py
lemmatizer_be/server/__init__.py
lemmatizer_be/server/main.py
lemmatizer_be/server/wsgi.py
lemmatizer_be-1.6.4.dist-info/METADATA
lemmatizer_be-1.6.4.dist-info/WHEEL
lemmatizer_be-1.6.4.dist-info/entry_points.txt
lemmatizer_be-1.6.4.dist-info/licenses/LICENSE
lemmatizer_be-1.6.4.dist-info/RECORD
