Metadata-Version: 2.4
Name: lemmatizer_be
Version: 1.6.4
Summary: Lemmatizer for Belarusian language (based on bnkorpus.info)
Project-URL: Documentation, https://github.com/alex-rusakevich/lemmatizer_be#readme
Project-URL: Issues, https://github.com/alex-rusakevich/lemmatizer_be/issues
Project-URL: Source, https://github.com/alex-rusakevich/lemmatizer_be
Author-email: Alexander Rusakevich <mr.alexander.rusakevich@gmail.com>
License-Expression: MIT
License-File: LICENSE
Classifier: Development Status :: 4 - Beta
Classifier: Programming Language :: Python
Classifier: Programming Language :: Python :: 3.8
Classifier: Programming Language :: Python :: 3.9
Classifier: Programming Language :: Python :: 3.10
Classifier: Programming Language :: Python :: 3.11
Classifier: Programming Language :: Python :: 3.12
Classifier: Programming Language :: Python :: Implementation :: CPython
Classifier: Programming Language :: Python :: Implementation :: PyPy
Requires-Python: >=3.8
Requires-Dist: a2wsgi
Requires-Dist: fastapi[standard]
Requires-Dist: lxml<6.0.0,>=5.3.0
Requires-Dist: requests<3.0.0,>=2.32.3
Requires-Dist: tqdm<5.0.0,>=4.67.1
Requires-Dist: uvicorn[standard]
